ppnrespeakerdemo/LICENSE
ppnrespeakerdemo/__init__.py
ppnrespeakerdemo/apa102.py
ppnrespeakerdemo/porcupine_demo.py
ppnrespeakerdemo-2.1.3.dist-info/METADATA
ppnrespeakerdemo-2.1.3.dist-info/WHEEL
ppnrespeakerdemo-2.1.3.dist-info/entry_points.txt
ppnrespeakerdemo-2.1.3.dist-info/top_level.txt
ppnrespeakerdemo-2.1.3.dist-info/RECORD
