Metadata-Version: 2.1
Name: ppnrespeakerdemo
Version: 2.1.3
Summary: ⚠️ DEPRECATED: This package is no longer maintained.
Home-page: https://github.com/Picovoice/porcupine
Author: Picovoice Inc.
Author-email: hello@picovoice.ai
Keywords: wake word,voice control,speech recognition,voice recognition,picovoice,porcupine,respeaker
Classifier: Development Status :: 5 - Production/Stable
Classifier: Intended Audience :: Developers
Classifier: License :: OSI Approved :: Apache Software License
Classifier: Operating System :: OS Independent
Classifier: Programming Language :: Python :: 3
Classifier: Topic :: Multimedia :: Sound/Audio :: Speech
Requires-Python: >=3.8
Requires-Dist: pvporcupine ==2.1.3
Requires-Dist: spidev
Requires-Dist: gpiozero
Requires-Dist: pvrecorder ==1.1.0
